{
  "users": [
    {
      "name": "Jay",
      "email": "jay@gmail.com",
      "password": "Jay@123",
      "id": "45e7"
    },
    {
      "name": "Ajay",
      "email": "ajay@gmail.com",
      "password": "Ajay@123",
      "id": "f7f6"
    },
    {
      "name": "Viay",
      "email": "vijay@gmail.com",
      "password": "Viay@123",
      "id": "4e73"
    },
    {
      "name": "Sanjay",
      "email": "sanjay@gmail.com",
      "password": "Sanjay@123",
      "id": "f879"
    },
    {
      "name": "Dhananjay",
      "email": "dhananjay@gmail.com",
      "password": "Dhananjay@123",
      "id": "09b6"
    },
    {
      "id": "90b8",
      "name": "Mohini",
      "email": "mohini@gmail.com",
      "password": "Mohini@123"
    }
  ]
}